pandas_flavor/__init__.py
pandas_flavor/__version__.py
pandas_flavor/register.py
pandas_flavor/xarray.py
pandas_flavor-0.6.0.dist-info/LICENSE
pandas_flavor-0.6.0.dist-info/METADATA
pandas_flavor-0.6.0.dist-info/WHEEL
pandas_flavor-0.6.0.dist-info/top_level.txt
pandas_flavor-0.6.0.dist-info/RECORD
